wfls/__init__.py
wfls/cli.py
wfls/conway.py
wfls/movinf.py
wfls/ui.py
wfls-0.1.5.dist-info/METADATA
wfls-0.1.5.dist-info/WHEEL
wfls-0.1.5.dist-info/entry_points.txt
wfls-0.1.5.dist-info/RECORD
