Metadata-Version: 2.1
Name: wfls
Version: 0.1.5
Summary: Custom CLI for personal use
Author: Juan Roy
Author-email: juanroy012@gmail.com
Requires-Python: >=3.9,<4.0
Classifier: Programming Language :: Python :: 3
Classifier: Programming Language :: Python :: 3.9
Classifier: Programming Language :: Python :: 3.10
Classifier: Programming Language :: Python :: 3.11
Classifier: Programming Language :: Python :: 3.12
Classifier: Programming Language :: Python :: 3.13
Requires-Dist: arrow (>=1.3.0,<2.0.0)
Requires-Dist: regex (>=2024.11.6,<2025.0.0)
Requires-Dist: requests (>=2.32.3,<3.0.0)
